{
  "firestore": {
    "rules": "firestore.rules",
    "indexes": "firestore.indexes.json"
  },
  "_comment_storage": "[DEPRECATED] Firebase Storage - Use Cloudflare R2 instead. See Docs_en/02_backend_database_design.md",
  "storage": {
    "rules": "storage.rules"
  },
  "emulators": {
    "auth": {
      "host": "0.0.0.0",
      "port": 9099
    },
    "firestore": {
      "host": "0.0.0.0",
      "port": 8080
    },
    "_comment_storage_emulator": "[DEPRECATED] Storage emulator kept for backward compatibility",
    "storage": {
      "host": "0.0.0.0",
      "port": 9199
    },
    "ui": {
      "enabled": true,
      "host": "0.0.0.0",
      "port": 4000,
      "webSocketPort": 9150
    },
    "hub": {
      "host": "0.0.0.0",
      "port": 4400
    },
    "logging": {
      "host": "0.0.0.0",
      "port": 4500
    }
  }
}
